[
  {
    "restaurant": "Hoffer",
    "soup": "0,33l Slepačí vývar s mäsom, zeleninou a niťovkami",
    "meals": [
      {
        "menu": 1,
        "name": "170 g Černohorský bravčový rezeň posypaný údeným syrom, zemiakové pyré, kyslé uhorky",
        "price": "8,90 €"
      },
      {
        "menu": 2,
        "name": "170 g Grilované kuracie medailónky na hríbovom cappuccine, dusená ryža",
        "price": "8,90 €"
      },
      {
        "menu": 3,
        "name": "300 g Zapekané penne \"ALA ŠÉF\" (kuracie mäso, niva, šampiňóny, kukurica) 1,3,7",
        "price": "8,90 €"
      },
      {
        "menu": 4,
        "name": "600 g Pizza podľa vlastného výberu (veľkosť classic), tatárska omáčka, kečup",
        "price": "8,90 €"
      },
      {
        "menu": 5,
        "name": "170 g Konfitované kačacie prsia, kapustové pyré z červenej kapusty, domáce zemiakové lokše (1,3,)",
        "price": "9,40 €"
      }
    ],
    "dessert": {
      "name": "Smotanová kocka s lesným ovocím",
      "weight": "50g",
      "delivery": false
    }
  },
  {
    "restaurant": "Quo Vadis",
    "type": "image_menu",
    "image_url": "https://www.quovadisnitra.sk/wp-content/uploads/2026/07/5-1-724x1024.jpg",
    "soup": "",
    "meals": []
  },
  {
    "restaurant": "Bellissimo",
    "type": "image_menu",
    "image_url": "https://bellissimonitra.com/wp-content/uploads/2026/07/menu-bellissimo-30-722x1024.jpg",
    "soup": "",
    "meals": []
  },
  {
    "restaurant": "Hospúdka u Slováka",
    "soup": "Karfiolový krém „Dubari“ s krutónmi 0,3 l (1,7)",
    "meals": [
      {
        "menu": 1,
        "name": "Zemiaková haruľa plnená bravčovým mäsom na spôsob tokáň, strúhaný slaný syr, sedliacka obloha 150 g (1,3,7)",
        "price": "9,90 €"
      },
      {
        "menu": 2,
        "name": "Vyprážaná kuracia pečeň, zemiakové pyré, hospodská tatárska omáčka 150 g (1,3,7)",
        "price": "9,90 €"
      },
      {
        "menu": 4,
        "name": "Vyprážaný rezeň z bravčového karé, alebo kuracích pŕs, majonézový šalát 150 g (1,3,7)",
        "price": "9,90 €"
      },
      {
        "menu": 5,
        "name": "Vyprážaný / grilovaný kurací rezeň podávaný na listovom miešanom šaláte, medovo-horčicový dresing s limetkovou šťavou 150 g (1,3,7,10)",
        "price": "9,50 €"
      },
      {
        "menu": 6,
        "name": "Losos z grilu, podávaný na listovom miešanom šaláte, jogurtovo – medový dresing, opekaná bagetka 150 g (1,4,7)",
        "price": "10,90 €"
      },
      {
        "menu": 7,
        "name": "Hovädzí rozbif krájaný za studena, podávaný na listovom miešanom šaláte, pikantný majonézový dresing, cesnaková bagetka 120 g (1,3,7)",
        "price": "10,90 €"
      },
      {
        "menu": 8,
        "name": "Grilovaný syr HERMELÍN, podávaný na listovom miešanom šaláte, tzatziky dresing 120 g (7)",
        "price": "9,50 €"
      }
    ]
  },
  {
    "restaurant": "Kotolňa",
    "soup": "0,40 l Zelerový krém s pórom, údeným mäsom a zemiakmi, chlieb",
    "meals": [
      {
        "name": "Kurací černohorský rezeň, popučené maslové zemiaky, údený syr, miešaný sladko - kyslý šalát",
        "price": "8,90 €"
      },
      {
        "name": "Pomaly dusené hovädzie plece, kôprová omáčka, parená knedľa",
        "price": "9,50 €"
      },
      {
        "name": "Pizza (paradajková omáčka, mozzarella, šunka, šampiňóny, kuracie kúsky) SK",
        "price": "8,70 €"
      },
      {
        "name": "Miešané šalátové listy, kurací gyros, kukurica, uhorka, bylinkový dresing, pizza chlieb",
        "price": "8,50 €"
      },
      {
        "name": "Krémové arborio rizoto so zeleným hráškom, parmezánom a bravčovou panenkou",
        "price": "8,90 €"
      },
      {
        "name": "Pšeničná tortilla s grilovaným halloumi (mango majonéza, polníček, halloumi syr, uhorka), tenké hranolky",
        "price": "8,90 €"
      }
    ]
  }
]