[
  {
    "restaurant": "Hoffer",
    "soup": "",
    "meals": []
  },
  {
    "restaurant": "Quo Vadis",
    "type": "link_menu",
    "menu_url": "https://www.quovadisnitra.sk/tyzdenne-menu/",
    "soup": "",
    "meals": []
  },
  {
    "restaurant": "Kotolňa",
    "soup": "0,40 l Hrachová s klobáskou a zeleninou, chlieb",
    "meals": [
      {
        "name": "150 g Pomaly pečená bravčová krkovička, sedliacke paprikové zemiaky na cibuľke, nakladaná cvikla",
        "price": 8.7
      },
      {
        "name": "150 g Kuracie stripsy v korenenej panko strúhanke a kórejskej bbq marináde, jazmínová ryža, mladá cibuľka, japonská majonéza, sezam Cena pre donášku a osobný odber:",
        "price": 8.7
      },
      {
        "name": "620 g Pizza Smotanová delikatesa (smotana, mozzarella, šunka, slanina, niva, kukurica)",
        "price": 8.7
      },
      {
        "name": "250 g Miešané šalátové listy, bravčová panenka na grile, sušené paradajky, slaninka, parmezán, bylinkový dresing, pizza chlieb Cena pre donášku a osobný odber:",
        "price": 8.9
      },
      {
        "name": "150 g Kuracie prsia na grile, syrový krém, hranolky, šalátik Cena pre donášku a osobný odber:",
        "price": 8.7
      },
      {
        "name": "350 g Rigatoni s bazalkovým pestom, pečenými cherry paradajkami a parmezánom",
        "price": 8.5
      }
    ]
  }
]